sphinx_kr_theme/__init__.py
sphinx_kr_theme/flask_theme_support.py
sphinx_kr_theme/kr/layout.html
sphinx_kr_theme/kr/relations.html
sphinx_kr_theme/kr/theme.conf
sphinx_kr_theme/kr/static/flasky.css_t
sphinx_kr_theme/kr/static/small_flask.css
sphinx_kr_theme/kr_small/layout.html
sphinx_kr_theme/kr_small/theme.conf
sphinx_kr_theme/kr_small/static/flasky.css_t
sphinx_kr_theme-0.2.1.dist-info/DESCRIPTION.rst
sphinx_kr_theme-0.2.1.dist-info/entry_points.txt
sphinx_kr_theme-0.2.1.dist-info/METADATA
sphinx_kr_theme-0.2.1.dist-info/metadata.json
sphinx_kr_theme-0.2.1.dist-info/RECORD
sphinx_kr_theme-0.2.1.dist-info/top_level.txt
sphinx_kr_theme-0.2.1.dist-info/WHEEL
