Metadata-Version: 2.0
Name: sphinx-kr-theme
Version: 0.2.1
Summary: The third-part package of kennethreitz/kr-sphinx-themes.
Home-page: https://github.com/tonyseek/sphinx-kr-theme
Author: Jiangge Zhang
Author-email: tonyseek@gmail.com
License: MIT
Platform: UNKNOWN
Classifier: Development Status :: 4 - Beta
Classifier: License :: OSI Approved :: BSD License
Classifier: Intended Audience :: Developers
Classifier: Programming Language :: Python :: 2
Classifier: Programming Language :: Python :: 2.7
Classifier: Programming Language :: Python :: 3
Classifier: Programming Language :: Python :: 3.3
Classifier: Programming Language :: Python :: 3.4
Classifier: Operating System :: OS Independent
Classifier: Topic :: Documentation
Classifier: Topic :: Software Development :: Documentation
